eu_cbm_hat/__init__.py
eu_cbm_hat/constants.py
eu_cbm_hat/bud/__init__.py
eu_cbm_hat/bud/adapt_age_classes.py
eu_cbm_hat/bud/associations.py
eu_cbm_hat/bud/input_data.py
eu_cbm_hat/bud/output.py
eu_cbm_hat/bud/post_processor.py
eu_cbm_hat/bud/test_data.py
eu_cbm_hat/cbm/__init__.py
eu_cbm_hat/cbm/cbm_vars_to_df.py
eu_cbm_hat/cbm/climate_growth_modifier.py
eu_cbm_hat/cbm/dynamic.py
eu_cbm_hat/cbm/simulation.py
eu_cbm_hat/combos/__init__.py
eu_cbm_hat/combos/base_combo.py
eu_cbm_hat/combos/historical.py
eu_cbm_hat/combos/ia_2040.py
eu_cbm_hat/combos/reference.py
eu_cbm_hat/core/__init__.py
eu_cbm_hat/core/continent.py
eu_cbm_hat/core/country.py
eu_cbm_hat/core/runner.py
eu_cbm_hat/crcf/__init__.py
eu_cbm_hat/crcf/country_simulator.py
eu_cbm_hat/crcf/driver_database.py
eu_cbm_hat/crcf/driver_netcdf.py
eu_cbm_hat/crcf/runner.py
eu_cbm_hat/info/__init__.py
eu_cbm_hat/info/aidb.py
eu_cbm_hat/info/clim_adjust.py
eu_cbm_hat/info/clim_adjust_common_input.py
eu_cbm_hat/info/fluxes.py
eu_cbm_hat/info/harvest.py
eu_cbm_hat/info/input_data.py
eu_cbm_hat/info/internal_data.py
eu_cbm_hat/info/orig_data.py
eu_cbm_hat/info/output_data.py
eu_cbm_hat/info/silviculture.py
eu_cbm_hat/launch/__init__.py
eu_cbm_hat/launch/associations.py
eu_cbm_hat/launch/create_json.py
eu_cbm_hat/plot/lulucf_plots.py
eu_cbm_hat/plot/npp.py
eu_cbm_hat/plot/scenarios.py
eu_cbm_hat/post_processor/__init__.py
eu_cbm_hat/post_processor/agg_combos.py
eu_cbm_hat/post_processor/area.py
eu_cbm_hat/post_processor/convert.py
eu_cbm_hat/post_processor/diagnostic.py
eu_cbm_hat/post_processor/growth_curve.py
eu_cbm_hat/post_processor/harvest.py
eu_cbm_hat/post_processor/hwp.py
eu_cbm_hat/post_processor/hwp_common_input.py
eu_cbm_hat/post_processor/hwp_substitution.py
eu_cbm_hat/post_processor/nai.py
eu_cbm_hat/post_processor/natural_disturbances.py
eu_cbm_hat/post_processor/npp.py
eu_cbm_hat/post_processor/orig_data_stats.py
eu_cbm_hat/post_processor/select_hwp_scenario.py
eu_cbm_hat/post_processor/sink.py
eu_cbm_hat-2.1.2.dist-info/licenses/LICENCE.txt
eu_cbm_hat-2.1.2.dist-info/licenses/NOTICE.txt
eu_cbm_hat-2.1.2.dist-info/METADATA
eu_cbm_hat-2.1.2.dist-info/WHEEL
eu_cbm_hat-2.1.2.dist-info/top_level.txt
eu_cbm_hat-2.1.2.dist-info/RECORD
