Metadata-Version: 2.4
Name: eu_cbm_hat
Version: 2.1.2
Summary: eu_cbm_hat is a python package for running carbon budget simulations.
Home-page: https://gitlab.com/bioeconomy/eu_cbm/eu_cbm_hat
Author: Lucas Sinclair
Author-email: lucas.sinclair@me.com
Maintainer: Paul Rougieux
License: EUPL
Requires-Python: >=3.8
License-File: LICENCE.txt
License-File: NOTICE.txt
Requires-Dist: autopaths>=1.6.0
Requires-Dist: plumbing>=2.11.1
Requires-Dist: pymarktex>=1.4.6
Requires-Dist: pandas
Requires-Dist: simplejson
Requires-Dist: pyyaml
Requires-Dist: tqdm
Requires-Dist: p_tqdm
Requires-Dist: pyarrow
Requires-Dist: numexpr
Provides-Extra: extras
Requires-Dist: pystache; extra == "extras"
Requires-Dist: matplotlib; extra == "extras"
Dynamic: author
Dynamic: author-email
Dynamic: description
Dynamic: description-content-type
Dynamic: home-page
Dynamic: license
Dynamic: license-file
Dynamic: maintainer
Dynamic: provides-extra
Dynamic: requires-dist
Dynamic: requires-python
Dynamic: summary
